reflex_calendar/__init__.py
reflex_calendar/calendar.py
reflex_calendar/calendar.pyi
reflex_calendar-0.0.6.dist-info/METADATA
reflex_calendar-0.0.6.dist-info/WHEEL
reflex_calendar-0.0.6.dist-info/top_level.txt
reflex_calendar-0.0.6.dist-info/RECORD
