Metadata-Version: 2.2
Name: reflex-calendar
Version: 0.0.6
Summary: Reflex custom component calendar
Author-email: Thomas Brandého <thomas.brandeho@gmail.com>
License: Apache-2.0
Project-URL: Homepage, https://github.com/Lendemor/reflex-calendar
Keywords: reflex,reflex-custom-components
Classifier: Development Status :: 4 - Beta
Requires-Python: >=3.9
Requires-Dist: reflex>=0.6.0
Provides-Extra: dev
Requires-Dist: build; extra == "dev"
Requires-Dist: twine; extra == "dev"
